xit/books/__init__.py
xit_books-0.1.0.dist-info/LICENSE
xit_books-0.1.0.dist-info/WHEEL
xit_books-0.1.0.dist-info/METADATA
xit_books-0.1.0.dist-info/RECORD
